cpematcher/__init__.py
cpematcher/core.py
cpematcher/utils.py
cpematcher/version.py
cpematcher_ng-1.1.0.dist-info/LICENSE.md
cpematcher_ng-1.1.0.dist-info/METADATA
cpematcher_ng-1.1.0.dist-info/WHEEL
cpematcher_ng-1.1.0.dist-info/RECORD
